[
  {
    "path": ".DS_Store",
    "size": 6148,
    "sha1": "ab256be89b2cb8bcdfba7d2d6ad9aaa8a142ea23",
    "ext": ""
  },
  {
    "path": ".github/workflows/ci.yml",
    "size": 522,
    "sha1": "b7b7389d29fd0c8cdff92c8f4fa946ee13268397",
    "ext": ".yml"
  },
  {
    "path": ".gitignore",
    "size": 5,
    "sha1": "a08af1b380b5b3f4ca934c9315513cbd39e63b09",
    "ext": ""
  },
  {
    "path": ".selene/roblox.toml",
    "size": 88,
    "sha1": "083240df21aa3944d59b5e207837254088e165be",
    "ext": ".toml"
  },
  {
    "path": ".vscode/tasks.json",
    "size": 686,
    "sha1": "32bf1e1f91741bbda96fa3ed5c882faad8e4b5d6",
    "ext": ".json"
  },
  {
    "path": "AGENTS.local.md",
    "size": 1037,
    "sha1": "a02576dd7384fce6cddfb057c1d675144adeb470",
    "ext": ".md"
  },
  {
    "path": "AUDIT_REPORT.md",
    "size": 8668,
    "sha1": "ce030a085136eba79016482b5b3552343dc72b9c",
    "ext": ".md"
  },
  {
    "path": "LICENSE",
    "size": 1066,
    "sha1": "14e693b1b1f710093d6f802367b1098856003961",
    "ext": ""
  },
  {
    "path": "PROJECT_TREE.txt",
    "size": 861,
    "sha1": "d15470c27e748b5e02cafd5bae9cdf4201a3901c",
    "ext": ".txt"
  },
  {
    "path": "README.md",
    "size": 206,
    "sha1": "6448a4a2acd96d5f4f10de0f774cb10a354dcb88",
    "ext": ".md"
  },
  {
    "path": "default.project.json",
    "size": 1358,
    "sha1": "e40dfb704bad87e8432d7a057c06820fcc3fe836",
    "ext": ".json"
  },
  {
    "path": "docs/AI_Workflow.md",
    "size": 934,
    "sha1": "66a71d5e01c0102a5f871485de33b1490d286861",
    "ext": ".md"
  },
  {
    "path": "docs/ARCHITECTURE.md",
    "size": 8013,
    "sha1": "338869c86499a4b634b32f4c53106385cd2b4ada",
    "ext": ".md"
  },
  {
    "path": "docs/ASSET_PIPELINE.md",
    "size": 418,
    "sha1": "2f8122b584b24ddf416b32c5bb7379bc44934cb6",
    "ext": ".md"
  },
  {
    "path": "docs/CHANGELOG.md",
    "size": 3138,
    "sha1": "6b8a27da4b34f7e13832a177b2fa510854f8ad2d",
    "ext": ".md"
  },
  {
    "path": "docs/CLEANUP_ACTIONS.md",
    "size": 1177,
    "sha1": "4c760cfc957e06c089e5a49784d5603ed2259a6d",
    "ext": ".md"
  },
  {
    "path": "docs/CLEANUP_REPORT.md",
    "size": 20892,
    "sha1": "559125923db96fb6fa56d3bbca7bbdc4c3203508",
    "ext": ".md"
  },
  {
    "path": "docs/CODEX_BASELINE.txt",
    "size": 845,
    "sha1": "e6288df051a5d2916536c2b575a648b5582dd178",
    "ext": ".txt"
  },
  {
    "path": "docs/ECONOMY.md",
    "size": 4821,
    "sha1": "3e87f4efef3a2ccca911f0614bf62a9d50931813",
    "ext": ".md"
  },
  {
    "path": "docs/PROJECT_SCOPE.md",
    "size": 682,
    "sha1": "6d1f55d135995a4be87607454d6c14fc26a7e85a",
    "ext": ".md"
  },
  {
    "path": "docs/README.md",
    "size": 5343,
    "sha1": "313c107d71ee48486b9928e83b7c0b17d1bf0a02",
    "ext": ".md"
  },
  {
    "path": "docs/RECOVERY.md",
    "size": 6084,
    "sha1": "66b49faf5f8311a2295242728f483a6382140450",
    "ext": ".md"
  },
  {
    "path": "docs/REFACTORING_GUIDE.md",
    "size": 860,
    "sha1": "c8ff7a6694565216549a6b65be5b4881d43f81d6",
    "ext": ".md"
  },
  {
    "path": "docs/SETUP_GUIDE.md",
    "size": 830,
    "sha1": "baccd60cdade0a7b7e93868cfaf142de511a4635",
    "ext": ".md"
  },
  {
    "path": "docs/STYLE.md",
    "size": 623,
    "sha1": "386020bcbe66ec400f2f8a1a2ae54590277f43f2",
    "ext": ".md"
  },
  {
    "path": "docs/WORLD_BLUEPRINT.md",
    "size": 5253,
    "sha1": "cfbceb45f304c36c25afcd2e699256cdbeda87f2",
    "ext": ".md"
  },
  {
    "path": "docs/_misc/Untitled spreadsheet.gsheet",
    "size": 175,
    "sha1": "12a3ab10fd0fdd95fd3a0b25a62cdf2e585c646a",
    "ext": ".gsheet"
  },
  {
    "path": "package.json",
    "size": 86,
    "sha1": "1baa0afc5fbc301760600df9a96e6e00935d3a82",
    "ext": ".json"
  },
  {
    "path": "robot-collectors-new-V1.rbxlx",
    "size": 1162,
    "sha1": "ee298e5411ce72e392b40947f630a1e49cddbbee",
    "ext": ".rbxlx"
  },
  {
    "path": ".gitignore",
    "size": 160,
    "sha1": "e37df97276db2585a59431039dbdacd1962c192a",
    "ext": ""
  },
  {
    "path": "default.project.json",
    "size": 615,
    "sha1": "c03d30121637fa190a2c9a31ea171bd65bd06820",
    "ext": ".json"
  },
  {
    "path": "scripts/_util_rojo.py",
    "size": 2650,
    "sha1": "724392b890c5593f407ed90d23eeb9c94af77b46",
    "ext": ".py"
  },
  {
    "path": "scripts/full_manifest.py",
    "size": 11795,
    "sha1": "b859560779c152b9b85ee5f76ee64f9229dcd6aa",
    "ext": ".py"
  },
  {
    "path": "scripts/repo_migrate_flatten_v1.py",
    "size": 16434,
    "sha1": "9ca538a4d0feaebc81a318956e132385f31d149d",
    "ext": ".py"
  },
  {
    "path": "selene.toml",
    "size": 244,
    "sha1": "49856e1a3f713dc879dc5308ad13dcf57264e5e2",
    "ext": ".toml"
  },
  {
    "path": "sourcemap.json",
    "size": 2593,
    "sha1": "fa605d9a0e0ba9db04e72ce994c52afe670d80be",
    "ext": ".json"
  },
  {
    "path": "src/ServerScriptService/RunOnce.server.luau",
    "size": 976,
    "sha1": "ff793e351b33eaefabdb3c5bf34d2be5876ca2fe",
    "ext": ".luau"
  },
  {
    "path": "src/client/.keep",
    "size": 0,
    "sha1": "0",
    "ext": ""
  },
  {
    "path": "src/client/ClickProbe.client.luau",
    "size": 1332,
    "sha1": "c12ac59444ee6625881cccc99782d98bc0080cb4",
    "ext": ".luau"
  },
  {
    "path": "src/client/CommandUI.client.luau",
    "size": 8011,
    "sha1": "f5ae46b34bf8105a826d435cab541a60ec4cf01e",
    "ext": ".luau"
  },
  {
    "path": "src/client/DebugPaverWatch.client.luau",
    "size": 1925,
    "sha1": "f9a9fe729d8618fd7dffadfef9c4bf6fa1e8a8ee",
    "ext": ".luau"
  },
  {
    "path": "src/client/DumpScrap.client.luau",
    "size": 507,
    "sha1": "468e4bc570d4e5e1563bffa58d0792e3ff8f106f",
    "ext": ".luau"
  },
  {
    "path": "src/client/HatchFX.client.luau",
    "size": 591,
    "sha1": "3fdb4ddcab578b0ad34b263eada2c354595010d2",
    "ext": ".luau"
  },
  {
    "path": "src/client/HideResourceOverlays.client.luau",
    "size": 1999,
    "sha1": "6b5a9f18b20082a0173932443f016be7cf3c5cb4",
    "ext": ".luau"
  },
  {
    "path": "src/client/Main.client.luau",
    "size": 708,
    "sha1": "5a956514a4af61a150073b7c3f8cbfc1a7d7cb6d",
    "ext": ".luau"
  },
  {
    "path": "src/client/NukeNearDoor.client.luau",
    "size": 1439,
    "sha1": "cca89c7e5ddb8ea8cab5664ae42892410acaf824",
    "ext": ".luau"
  },
  {
    "path": "src/client/ZoneToast.client.luau",
    "size": 2797,
    "sha1": "5ee1dc8a57f6558699ca3387faf3bca9f1607eff",
    "ext": ".luau"
  },
  {
    "path": "src/client/init.client.luau",
    "size": 34,
    "sha1": "f65bb9deefca9c97ae488bbe2b91738e4d303098",
    "ext": ".luau"
  },
  {
    "path": "src/client/modules/MissionsHUD.client.luau",
    "size": 6826,
    "sha1": "e8d61a5ec718a81e205111987e29b286203ae009",
    "ext": ".luau"
  },
  {
    "path": "src/client/modules/ResourceFX.client.luau",
    "size": 4218,
    "sha1": "09ca488b85545e37936d160851cf40f3e6f5e0cd",
    "ext": ".luau"
  },
  {
    "path": "src/client/ui/ResourceHUD.client.luau",
    "size": 2382,
    "sha1": "41c37171a6a94984a9de9005286912d1f264c09c",
    "ext": ".luau"
  },
  {
    "path": "src/client/ui/RightDock.client.luau",
    "size": 4401,
    "sha1": "c70da092b275c05c1c73dbdd2eed5d80310998b4",
    "ext": ".luau"
  },
  {
    "path": "src/server/.keep",
    "size": 0,
    "sha1": "0",
    "ext": ""
  },
  {
    "path": "src/server/DumpScrap.server.luau",
    "size": 507,
    "sha1": "096f6d65af6227fe38c16160811b368d466631ce",
    "ext": ".luau"
  },
  {
    "path": "src/server/HideResourceOverlays.server.luau",
    "size": 2749,
    "sha1": "0e21bceec4281484ac4887d35d6f6143a74d130c",
    "ext": ".luau"
  },
  {
    "path": "src/server/MissionService.server.luau",
    "size": 5803,
    "sha1": "01678b9679b7a6093b3390a605650aff4ac03781",
    "ext": ".luau"
  },
  {
    "path": "src/server/Remotes.server.luau",
    "size": 1570,
    "sha1": "4b96e2b50ea2bad5a9e4af36478ff5646a73346f",
    "ext": ".luau"
  },
  {
    "path": "src/server/RogueGroundKiller.server.luau",
    "size": 1769,
    "sha1": "72f1778a1618f73b728f77e2598a50420bb6bd3e",
    "ext": ".luau"
  },
  {
    "path": "src/server/RunOnce.server.luau",
    "size": 976,
    "sha1": "ff793e351b33eaefabdb3c5bf34d2be5876ca2fe",
    "ext": ".luau"
  },
  {
    "path": "src/server/ScrapHotfix.server.luau",
    "size": 1297,
    "sha1": "ae03e6214aec8c0caa019d48316c63b330dacac1",
    "ext": ".luau"
  },
  {
    "path": "src/server/ScrapTerminator.server.luau",
    "size": 2433,
    "sha1": "816f5db05c4258eacbc95543535846f1434d61e3",
    "ext": ".luau"
  },
  {
    "path": "src/server/WatchNewParts.server.luau",
    "size": 750,
    "sha1": "763dbd503f861658ad4e96c1eedffa7a6d589baa",
    "ext": ".luau"
  },
  {
    "path": "src/server/bootstrap.server.luau",
    "size": 1686,
    "sha1": "22a07c922b287d543c2cf4f2d082d749b1929c96",
    "ext": ".luau"
  },
  {
    "path": "src/server/init.server.luau",
    "size": 34,
    "sha1": "6d78dbc65fb3e28619857cc1c34dc3e76955b470",
    "ext": ".luau"
  },
  {
    "path": "src/server/modules/.keep",
    "size": 7,
    "sha1": "c51b5415bd28b9b42852a0b6c1112aeb7e981f18",
    "ext": ""
  },
  {
    "path": "src/server/modules/PartFactory.luau",
    "size": 1124,
    "sha1": "6b90e50f4db528dd915bcbe9028070f88a24fc23",
    "ext": ".luau"
  },
  {
    "path": "src/server/services/MissionService.server.luau",
    "size": 9179,
    "sha1": "6c15376a67a657c8e7776691d30df8772810e1a8",
    "ext": ".luau"
  },
  {
    "path": "src/server/services/ResourceService.server.luau",
    "size": 5508,
    "sha1": "4e6cc4c29f40949a47aadf87816d8cb3bd53818c",
    "ext": ".luau"
  },
  {
    "path": "src/server/spawn_guard.server.luau",
    "size": 2713,
    "sha1": "f9228788bbef39696666a77f7a29bd1d6f1f94d7",
    "ext": ".luau"
  },
  {
    "path": "src/server/tests/TestRunner.server.luau",
    "size": 1286,
    "sha1": "c4bf77cb2a0ed61e2d02dc836e58aa7f3714e2ef",
    "ext": ".luau"
  },
  {
    "path": "src/server/tests/specs/DoorPlane_spec 2.luau",
    "size": 1243,
    "sha1": "0aa42448469988cbc538511487d3f2fb7b0f91ca",
    "ext": ".luau"
  },
  {
    "path": "src/server/tests/specs/DoorPlane_spec.luau",
    "size": 1243,
    "sha1": "0aa42448469988cbc538511487d3f2fb7b0f91ca",
    "ext": ".luau"
  },
  {
    "path": "src/server/tests/specs/PathSampler_spec 2.luau",
    "size": 974,
    "sha1": "deb9f011f38dd9de99b157e85441390cc7f5983a",
    "ext": ".luau"
  },
  {
    "path": "src/server/tests/specs/PathSampler_spec.luau",
    "size": 974,
    "sha1": "deb9f011f38dd9de99b157e85441390cc7f5983a",
    "ext": ".luau"
  },
  {
    "path": "src/server/world/AutoDoorManager.server.luau",
    "size": 80,
    "sha1": "a83e2f13dc99ebc6de28400b153ccc9d4a38c375",
    "ext": ".luau"
  },
  {
    "path": "src/server/world/CleanupResources.server.luau",
    "size": 3814,
    "sha1": "3e4b8a7a023afde8861c24882c3409b09103b87b",
    "ext": ".luau"
  },
  {
    "path": "src/server/world/Garage/Animate.luau",
    "size": 954,
    "sha1": "1134b7647f0e22c4248e92442dd1b47da306bad4",
    "ext": ".luau"
  },
  {
    "path": "src/server/world/Garage/Component.luau",
    "size": 20813,
    "sha1": "f24aef36c17e74da5091937532487aad91db2337",
    "ext": ".luau"
  },
  {
    "path": "src/server/world/Garage/Debug.server.luau",
    "size": 2573,
    "sha1": "c5a9804574ab32a526d49b30d09690b0d9e5be64",
    "ext": ".luau"
  },
  {
    "path": "src/server/world/Garage/Fixup.luau",
    "size": 5017,
    "sha1": "9d8f251f44a6d8e527e0151da71ae761d6286da3",
    "ext": ".luau"
  },
  {
    "path": "src/server/world/Garage/Interior.luau",
    "size": 20134,
    "sha1": "1f483580820fde6960e19cf600660cc0f12c2762",
    "ext": ".luau"
  },
  {
    "path": "src/server/world/Garage/Shows/Hatch.luau",
    "size": 9162,
    "sha1": "d2aba44a04b8072c782c15283ddef7c0399dcfea",
    "ext": ".luau"
  },
  {
    "path": "src/server/world/Remotes.server.luau",
    "size": 2235,
    "sha1": "485a2a4b484a310e7f8bf46bdf4a3cc92b636c39",
    "ext": ".luau"
  },
  {
    "path": "src/server/world/ResourceSpawner.server.luau",
    "size": 7257,
    "sha1": "1fd8bdda6042c892636ff86d4c702fc26086893e",
    "ext": ".luau"
  },
  {
    "path": "src/server/world/Spawn.luau",
    "size": 927,
    "sha1": "f702a05a350a3a6baa54992a6bb38e2b3e5af132",
    "ext": ".luau"
  },
  {
    "path": "src/server/world/TerrainLoader.server.luau",
    "size": 5048,
    "sha1": "66135e66d6b9da232f3c3ee593045448f4e57e07",
    "ext": ".luau"
  },
  {
    "path": "src/server/world/WorldBoot.luau",
    "size": 9457,
    "sha1": "3dd7afb7012d9c33c902b7726fd38614b5461ff2",
    "ext": ".luau"
  },
  {
    "path": "src/server/world/WorldBoot.luau.bak_20251016-114919",
    "size": 9523,
    "sha1": "c9631f643f256bf585d274d9374f10ad72d077ce",
    "ext": ".bak_20251016-114919"
  },
  {
    "path": "src/server/world/WorldInteract.server.luau",
    "size": 15998,
    "sha1": "0d27162321081fd8d74f09eb3d28ac3f7bcadcef",
    "ext": ".luau"
  },
  {
    "path": "src/server/world/WorldInteract.server.luau.bak_20251016-114925",
    "size": 15726,
    "sha1": "86652bf79074d924501fb33e1e7f5082b94736a3",
    "ext": ".bak_20251016-114925"
  },
  {
    "path": "src/server/world/ZoneTrigger.server.luau",
    "size": 3739,
    "sha1": "5b59945e7977399b4c6a675385bb9a7814cadc5b",
    "ext": ".luau"
  },
  {
    "path": "src/server/world/bootstrap.server.luau",
    "size": 5513,
    "sha1": "0f442e2de67b8c366da2fde796badc456d221385",
    "ext": ".luau"
  },
  {
    "path": "src/server/world/spawn_guard.server.luau",
    "size": 2713,
    "sha1": "f9228788bbef39696666a77f7a29bd1d6f1f94d7",
    "ext": ".luau"
  },
  {
    "path": "src/server/world/zzz_mount_diag.server.luau",
    "size": 604,
    "sha1": "a001cfd8da0d0b2cf789dd3c91ad44729268c76a",
    "ext": ".luau"
  },
  {
    "path": "src/server/world/zzz_server_banner.server.luau",
    "size": 72,
    "sha1": "99e4783d1ad4fd2730943d653cccc841a4d8721c",
    "ext": ".luau"
  },
  {
    "path": "src/server/zzz_mount_diag.server.luau",
    "size": 604,
    "sha1": "a001cfd8da0d0b2cf789dd3c91ad44729268c76a",
    "ext": ".luau"
  },
  {
    "path": "src/server/zzz_server_banner.server.luau",
    "size": 72,
    "sha1": "99e4783d1ad4fd2730943d653cccc841a4d8721c",
    "ext": ".luau"
  },
  {
    "path": "src/server_modules/.keep",
    "size": 0,
    "sha1": "0",
    "ext": ""
  },
  {
    "path": "src/server_modules/BuildGuard.luau",
    "size": 339,
    "sha1": "6cb92faa72cfc0fafc0d2fc6badddb2705b77946",
    "ext": ".luau"
  },
  {
    "path": "src/server_modules/DoorPlane.luau",
    "size": 853,
    "sha1": "1db1be852d5b4a2d136599ef30814081f4339585",
    "ext": ".luau"
  },
  {
    "path": "src/server_modules/PadAudit.luau",
    "size": 2312,
    "sha1": "bfc314d82ed2643b4bd4bee6781f6bd1031c3e45",
    "ext": ".luau"
  },
  {
    "path": "src/server_modules/ProgressionService.luau",
    "size": 1340,
    "sha1": "7e26ffe0850c7391e9fc8599f40ea3c08cbf703f",
    "ext": ".luau"
  },
  {
    "path": "src/server_modules/QuestService.luau",
    "size": 3187,
    "sha1": "13855dc11107df06a1d1cae66bbac078361d16ab",
    "ext": ".luau"
  },
  {
    "path": "src/shared/.keep",
    "size": 0,
    "sha1": "0",
    "ext": ""
  },
  {
    "path": "src/shared/Hello.luau",
    "size": 45,
    "sha1": "fdc469f4a49057196275141c16be1bd5c4c167e4",
    "ext": ".luau"
  },
  {
    "path": "src/shared/ResourceDefs.luau",
    "size": 1486,
    "sha1": "f8823c5162b45677b8344dd0a32cba6fcf37d79b",
    "ext": ".luau"
  },
  {
    "path": "src/shared/config/CollectConfig.luau",
    "size": 616,
    "sha1": "c780f54e641837ba6e22d5fd5e660bcfda9b55fc",
    "ext": ".luau"
  },
  {
    "path": "src/shared/config/GameConstants.luau",
    "size": 655,
    "sha1": "63de80727c12f6c6c97807d930aa54e0fe67e06c",
    "ext": ".luau"
  },
  {
    "path": "src/shared/config/MissionDefs.luau",
    "size": 4693,
    "sha1": "82d971b85b257e2cce8213328571e2114841640b",
    "ext": ".luau"
  },
  {
    "path": "src/shared/config/Quests.luau",
    "size": 1140,
    "sha1": "09dec1dea2785962109a7cecb9bd6e83a08cffee",
    "ext": ".luau"
  },
  {
    "path": "src/shared/config/Unlocks.luau",
    "size": 843,
    "sha1": "01563dfde449e280f4348556a72af2ebe3df651b",
    "ext": ".luau"
  },
  {
    "path": "src/shared/utils/ResourceGuards.luau",
    "size": 1578,
    "sha1": "129ffc94ed82e00fac9290c7304c90b1f5e4c85c",
    "ext": ".luau"
  },
  {
    "path": "stylua.toml",
    "size": 178,
    "sha1": "1e43d947ded58f36ee3f565c6701f43bc69da798",
    "ext": ".toml"
  },
  {
    "path": "tools/cleanup_actions.py",
    "size": 9429,
    "sha1": "4580326006ac738a0d308360c5fc47dbc7b58284",
    "ext": ".py"
  },
  {
    "path": "tools/cleanup_project.py",
    "size": 16902,
    "sha1": "cefb6f362ef71b260dc3a7b317fc99b96c22be11",
    "ext": ".py"
  },
  {
    "path": "tools/scan_project.py",
    "size": 19203,
    "sha1": "d244b4ef857cf782b200b5aa917d5508c35e0232",
    "ext": ".py"
  },
  {
    "path": "world.rbxm",
    "size": 8394,
    "sha1": "139ec2b8c04b013ce2b01f14991e989df0f84ec1",
    "ext": ".rbxm"
  }
]